{
    "modules": [
        {
            "config": {
                "position": [
                    339,
                    95
                ]
            },
            "name": "New Model Object",
            "value": {
                "actionGroup": {
                    "_default0_list": true,
                    "_default1_show": true,
                    "_default2_new_create": false,
                    "_default3_edit_update": false,
                    "_default4_delete": false,
                    "customActions": []
                },
                "name": "Movie",
                "objectsettings": {
                    "addDeletedField": true,
                    "addHiddenField": true,
                    "addStarttimeEndtimeFields": true,
                    "aggregateRoot": true,
                    "categorizable": false,
                    "description": "",
                    "mapToTable": "",
                    "parentClass": "",
                    "sorting": false,
                    "type": "Entity",
                    "uid": "205933850114"
                },
                "propertyGroup": {
                    "properties": [
                        {
                            "allowedFileTypes": "",
                            "maxItems": "1",
                            "propertyDescription": "",
                            "propertyIsExcludeField": true,
                            "propertyIsRequired": false,
                            "propertyName": "originaltitle",
                            "propertyType": "String",
                            "uid": "239164550830"
                        },
                        {
                            "allowedFileTypes": "",
                            "maxItems": "1",
                            "propertyDescription": "",
                            "propertyIsExcludeField": true,
                            "propertyIsRequired": false,
                            "propertyName": "releasedate",
                            "propertyType": "String",
                            "uid": "1395347064643"
                        },
                        {
                            "allowedFileTypes": "",
                            "maxItems": "1",
                            "propertyDescription": "",
                            "propertyIsExcludeField": true,
                            "propertyIsRequired": false,
                            "propertyName": "title",
                            "propertyType": "String",
                            "uid": "520701362059"
                        },
                        {
                            "allowedFileTypes": "",
                            "maxItems": "1",
                            "propertyDescription": "",
                            "propertyIsExcludeField": true,
                            "propertyIsRequired": false,
                            "propertyName": "image",
                            "propertyType": "String",
                            "uid": "396104289735"
                        },
                        {
                            "allowedFileTypes": "",
                            "maxItems": "1",
                            "propertyDescription": "",
                            "propertyIsExcludeField": true,
                            "propertyIsRequired": false,
                            "propertyName": "backdroppath",
                            "propertyType": "String",
                            "uid": "283463399989"
                        },
                        {
                            "allowedFileTypes": "",
                            "maxItems": "1",
                            "propertyDescription": "",
                            "propertyIsExcludeField": true,
                            "propertyIsRequired": false,
                            "propertyName": "id",
                            "propertyType": "String",
                            "uid": "299463625428"
                        },
                        {
                            "allowedFileTypes": "",
                            "maxItems": "1",
                            "propertyDescription": "",
                            "propertyIsExcludeField": true,
                            "propertyIsRequired": false,
                            "propertyName": "popularity",
                            "propertyType": "String",
                            "uid": "75978542245"
                        },
                        {
                            "allowedFileTypes": "",
                            "maxItems": "1",
                            "propertyDescription": "",
                            "propertyIsExcludeField": true,
                            "propertyIsRequired": false,
                            "propertyName": "category",
                            "propertyType": "String",
                            "uid": "641019318909"
                        },
                        {
                            "allowedFileTypes": "",
                            "maxItems": "1",
                            "propertyDescription": "",
                            "propertyIsExcludeField": true,
                            "propertyIsRequired": false,
                            "propertyName": "filename",
                            "propertyType": "String",
                            "uid": "614359249403"
                        },
                        {
                            "allowedFileTypes": "",
                            "maxItems": "1",
                            "propertyDescription": "",
                            "propertyIsExcludeField": true,
                            "propertyIsRequired": false,
                            "propertyName": "year",
                            "propertyType": "String",
                            "uid": "681885579955"
                        },
                        {
                            "allowedFileTypes": "",
                            "maxItems": "1",
                            "propertyDescription": "",
                            "propertyIsExcludeField": true,
                            "propertyIsRequired": false,
                            "propertyName": "parental",
                            "propertyType": "String",
                            "uid": "1084701562397"
                        },
                        {
                            "allowedFileTypes": "",
                            "maxItems": "1",
                            "propertyDescription": "",
                            "propertyIsExcludeField": true,
                            "propertyIsRequired": false,
                            "propertyName": "overview",
                            "propertyType": "Text",
                            "uid": "939962600837"
                        },
                        {
                            "allowedFileTypes": "",
                            "maxItems": "1",
                            "propertyDescription": "",
                            "propertyIsExcludeField": true,
                            "propertyIsRequired": false,
                            "propertyName": "votes",
                            "propertyType": "Text",
                            "uid": "112794042143"
                        }
                    ]
                },
                "relationGroup": {
                    "relations": []
                }
            }
        }
    ],
    "properties": {
        "backendModules": [],
        "description": "",
        "emConf": {
            "category": "plugin",
            "custom_category": "",
            "dependsOn": "typo3 => 6.2\n",
            "disableLocalization": false,
            "disableVersioning": false,
            "sourceLanguage": "en",
            "state": "beta",
            "targetVersion": "6.2",
            "version": "0.0.1"
        },
        "extensionKey": "pmmoviebase",
        "name": "pm Moviebase",
        "originalExtensionKey": "pmmoviebase",
        "persons": [
            {
                "company": "pm-newmedia.com",
                "email": "moviedatabase@pm-newmedia.com",
                "name": "moviedatabase@pm-newmedia.com",
                "role": "Developer"
            }
        ],
        "plugins": [
            {
                "actions": {
                    "controllerActionCombinations": "",
                    "noncacheableActions": "",
                    "switchableActions": ""
                },
                "key": "pmmoviebase",
                "name": "pm MovieBase"
            }
        ],
        "vendorName": "Pmmoviebase"
    },
    "wires": [],
    "log": {
        "last_modified": "2015-06-15 11:43",
        "extension_builder_version": "6.2.0",
        "be_user": " (1)"
    }
}